CHANGELOG.md
LICENSE
LICENSE2
README.md
setup.py
.github/workflows/altmodule.yaml
.github/workflows/ci.yaml
test/test_zipfile.py
test/data/10000SalesRecords.csv
zipfile39/__init__.py
zipfile39/__main__.py
zipfile39/version.py
zipfile39/zipfile39.py
zipfile39.egg-info/PKG-INFO
zipfile39.egg-info/SOURCES.txt
zipfile39.egg-info/dependency_links.txt
zipfile39.egg-info/not-zip-safe
zipfile39.egg-info/requires.txt
zipfile39.egg-info/top_level.txt